bubbletea/__init__.py
bubbletea/cli.py
bubbletea/cryptocompare.py
bubbletea/charts/__init__.py
bubbletea/charts/area.py
bubbletea/charts/bar.py
bubbletea/charts/base.py
bubbletea/charts/colors.py
bubbletea/charts/combo.py
bubbletea/charts/helper.py
bubbletea/charts/heuristics.py
bubbletea/charts/line.py
bubbletea/charts/table.py
bubbletea/thegraph/__init__.py
bubbletea/thegraph/__core/SubgraphLoader.py
bubbletea/thegraph/__core/TheGraphEntity.py
bubbletea/thegraph/__core/__init__.py
bubbletea/thegraph/__core/schema_utils.py
bubbletea/transformers/__init__.py
bubbletea/transformers/timeseries.py
bubbletea/transformers/urlparser.py
BubbleTea_py-0.0.7.dist-info/METADATA
BubbleTea_py-0.0.7.dist-info/WHEEL
BubbleTea_py-0.0.7.dist-info/entry_points.txt
BubbleTea_py-0.0.7.dist-info/top_level.txt
BubbleTea_py-0.0.7.dist-info/RECORD
