Metadata-Version: 2.1
Name: BubbleTea-py
Version: 0.0.7
Summary: BubbleTea enables developers to quickly build any data applications on the emerging Web3 infrastructure.
Home-page: https://github.com/scout-cool/BubbleTea
Author: Supermax Tech.
Author-email: hello@scout.cool
License: UNKNOWN
Platform: UNKNOWN
Requires-Python: >=3.6
Requires-Dist: streamlit (==0.87.0)
Requires-Dist: graphql-core (==3.1.5)
Requires-Dist: st-flashcard (==0.0.5)
Requires-Dist: python-dotenv (==0.18.0)
Requires-Dist: streamlit-aggrid (==0.2.1)
